[
  {
    "id_img": "LoveLiveSunshine_836449_crop2608_1474958642",
    "lik": "UTb0sGqADnbLiHq9qhRMRkSRiLND0Tk7ctN8tpraiidbcEqMm6qDeeLBOcXoUbzqfpLlNzr0WWtxOUsnup/6MJVy4706IhQgSYlgwrgVRHU=",
    "thub": "UTb0sGqADnbLiHq9qhRMRkSRiLND0Tk7ctN8tpraiidbcEqMm6qDeeLBOcXoUbzqz4AOmlNMX4ilAzA5PnTE0ZVy4706IhQgSYlgwrgVRHU=",
    "albl": [
      "Girls",
      "Love Live Sunshine"
    ],
    "norl": [
      "You Watanabe",
      "Dia Kurosawa",
      "Yoshiko Tsushima"
    ],
    "spel": [
      "Girls Hair Black",
      "Girls Student",
      "Girls Short Hair",
      "Girls Hair Grey",
      "Girls Long Hair",
      "Girls Cute Cool",
      "Girls Smile",
      "Girls Tie Bows",
      "Girls Eyes Blue",
      "Girls Hair Brow"
    ],
    "i_top": 0,
    "i_newest": 0,
    "i_sgg": 0,
    "h_img": 1512,
    "w_img": 1064,
    "date_img_modified": 1645538815604,
    "file_size": "193.52 Kb"
  }
]