[
  {
    "id_img": "Crossover_786535_crop2608_-464082305",
    "lik": "UTb0sGqADnbLiHq9qhRMRkSRiLND0Tk7ctN8tpraiienFE5bNsiDWfI1ZgoGMf3PImUpolkp19LLDJwpQXOp7pVy4706IhQgSYlgwrgVRHU=",
    "thub": "UTb0sGqADnbLiHq9qhRMRkSRiLND0Tk7ctN8tpraiienFE5bNsiDWfI1ZgoGMf3PLP8iq2t9vrJ3ZZ3SYK5sYpVy4706IhQgSYlgwrgVRHU=",
    "albl": [
      "Crossover"
    ],
    "norl": [
      "Portgas D Ace",
      "Ichigo Kurosaki",
      "Sanji One Piece",
      "Ash Ketchum",
      "Erza Scarlet",
      "Roronoa Zoro",
      "Rin Tohsaka",
      "Natsu Dragneel",
      "Goku",
      "Lucy Heartfilia",
      "Asuna Yuuki",
      "Gohan Dragon Ball",
      "Kazuto Kirigaya",
      "Mei Misaki",
      "Pikachu",
      "Monkey D Luffy",
      "Kirito Sword Art Online",
      "Saber Fate Series",
      "Trunks Dragon Ball",
      "Trafalgar Law",
      "Rukia Kuchiki",
      "Vegeta Dragon Ball"
    ],
    "spel": [],
    "i_top": 0,
    "i_newest": 0,
    "i_sgg": 0,
    "h_img": 1085,
    "w_img": 763,
    "date_img_modified": 1645534832635,
    "file_size": "175.08 Kb"
  }
]