{
  "total": 56,
  "data": [
    {
      "id_img": "Original_855527_crop2608_-747583678",
      "lik": "UTb0sGqADnbLiHq9qhRMRkSRiLND0Tk7ctN8tpraiieUTMosr86kZgnMyWOM/gJrTiuKHOfKA/sNYppc96hJL5Vy4706IhQgSYlgwrgVRHU=",
      "thub": "UTb0sGqADnbLiHq9qhRMRkSRiLND0Tk7ctN8tpraiieUTMosr86kZgnMyWOM/gJrHqFy4rA0a9R7i+XO9eaTGpVy4706IhQgSYlgwrgVRHU=",
      "albl": [
        "Unrefined",
        "Original 7"
      ],
      "norl": [
        "Skeleton",
        "Ribbon",
        "Skull",
        "Fantasy",
        "Mask",
        "Rainbow",
        "Card"
      ],
      "spel": [],
      "i_top": 0,
      "i_newest": 0,
      "i_sgg": 0,
      "h_img": 1326,
      "w_img": 933,
      "date_img_modified": 1645542960047,
      "file_size": "238.46 Kb"
    },
    {
      "id_img": "Original_855527_crop2608_-1062309680",
      "lik": "UTb0sGqADnbLiHq9qhRMRkSRiLND0Tk7ctN8tpraiieXixb2RzKdCt3yBhmDWEEWaUcrytr/c3Zvrwb4UwgmqZVy4706IhQgSYlgwrgVRHU=",
      "thub": "UTb0sGqADnbLiHq9qhRMRkSRiLND0Tk7ctN8tpraiieXixb2RzKdCt3yBhmDWEEWm7cbx7EgUEKRAhj/BWJ23JVy4706IhQgSYlgwrgVRHU=",
      "albl": [
        "Girls",
        "Original 7"
      ],
      "norl": [
        "Skeleton",
        "Ribbon",
        "Skull",
        "Fantasy",
        "Mask",
        "Rainbow",
        "Card"
      ],
      "spel": [
        "Girls Hair Silver",
        "Girls Long Hair",
        "Girls Face Masks",
        "Girls Eyes Black",
        "Girls Kimono Yukata Cheongsam",
        "Girls Tie Bows"
      ],
      "i_top": 0,
      "i_newest": 0,
      "i_sgg": 0,
      "h_img": 1326,
      "w_img": 933,
      "date_img_modified": 1645542960129,
      "file_size": "215.49 Kb"
    },
    {
      "id_img": "Original_855532_crop2608_-1347009873",
      "lik": "UTb0sGqADnbLiHq9qhRMRkSRiLND0Tk7ctN8tpraiieWT8J5J+yvfQeNPdGo8va5DO1VVM4jbv2XB30O1Wi1f5Vy4706IhQgSYlgwrgVRHU=",
      "thub": "UTb0sGqADnbLiHq9qhRMRkSRiLND0Tk7ctN8tpraiieWT8J5J+yvfQeNPdGo8va527Mz2x3VMNzb4MVfZQ/Wj5Vy4706IhQgSYlgwrgVRHU=",
      "albl": [
        "Girls",
        "Original 7"
      ],
      "norl": [
        "Stars",
        "Ribbon",
        "Flower"
      ],
      "spel": [
        "Girls Hair Silver",
        "Girls Bell",
        "Girls Uniform",
        "Girls Long Hair",
        "Girls Cute Cool",
        "Girls Hair Blue",
        "Girls Smile",
        "Girls Tie Bows",
        "Girls Eyes Blue"
      ],
      "i_top": 0,
      "i_newest": 0,
      "i_sgg": 0,
      "h_img": 1200,
      "w_img": 844,
      "date_img_modified": 1645542960611,
      "file_size": "110.02 Kb"
    },
    {
      "id_img": "Original_855532_crop2608_-205942308",
      "lik": "UTb0sGqADnbLiHq9qhRMRkSRiLND0Tk7ctN8tpraiif02pnSvxujwpp3BIv31gvA39fYIF1jAOja/o9ql9x115Vy4706IhQgSYlgwrgVRHU=",
      "thub": "UTb0sGqADnbLiHq9qhRMRkSRiLND0Tk7ctN8tpraiif02pnSvxujwpp3BIv31gvAVectFseRgUqvX0mSrK0MkJVy4706IhQgSYlgwrgVRHU=",
      "albl": [
        "Girls",
        "Original 7"
      ],
      "norl": [
        "Stars",
        "Ribbon",
        "Flower"
      ],
      "spel": [
        "Girls Hair Silver",
        "Girls Hair White",
        "Girls Long Hair",
        "Girls Eyes Grey",
        "Girls Smile",
        "Girls Tie Bows"
      ],
      "i_top": 0,
      "i_newest": 0,
      "i_sgg": 0,
      "h_img": 1200,
      "w_img": 844,
      "date_img_modified": 1645542960667,
      "file_size": "113.08 Kb"
    },
    {
      "id_img": "Original_855619_crop2608_-882161863",
      "lik": "UTb0sGqADnbLiHq9qhRMRkSRiLND0Tk7ctN8tpraiidoznH9rQOv/KE5343BZlYIIAyERyag03OoidYYgyik5JVy4706IhQgSYlgwrgVRHU=",
      "thub": "UTb0sGqADnbLiHq9qhRMRkSRiLND0Tk7ctN8tpraiidoznH9rQOv/KE5343BZlYIASEffS+L0NugmuFM43N8WZVy4706IhQgSYlgwrgVRHU=",
      "albl": [
        "Girls",
        "Original 7"
      ],
      "norl": [
        "Ribbon"
      ],
      "spel": [
        "Girls Student",
        "Girls Hair Pink",
        "Girls Eyes Red",
        "Girls Long Hair",
        "Girls Cute Cool",
        "Girls Ears Neko",
        "Girls Tie Bows"
      ],
      "i_top": 0,
      "i_newest": 0,
      "i_sgg": 0,
      "h_img": 1025,
      "w_img": 721,
      "date_img_modified": 1645542961336,
      "file_size": "140.95 Kb"
    },
    {
      "id_img": "Original_855619_crop2608_-163603482",
      "lik": "UTb0sGqADnbLiHq9qhRMRkSRiLND0Tk7ctN8tpraiicXGUKqxmnc5EkKkTnVwlDzRyVxOXPQ63/awDZztwD8lpVy4706IhQgSYlgwrgVRHU=",
      "thub": "UTb0sGqADnbLiHq9qhRMRkSRiLND0Tk7ctN8tpraiicXGUKqxmnc5EkKkTnVwlDzz0fdxHus8tbyC9Ern8WE2ZVy4706IhQgSYlgwrgVRHU=",
      "albl": [
        "Girls",
        "Original 7"
      ],
      "norl": [
        "Ribbon"
      ],
      "spel": [
        "Girls Hair Orange",
        "Girls Sharp Canine Tooth",
        "Girls Uniform",
        "Girls Hair Yellow",
        "Girls Long Hair",
        "Girls Cute Cool",
        "Girls Ears Neko",
        "Girls Smile",
        "Girls Tie Bows",
        "Girls Eyes Blue"
      ],
      "i_top": 0,
      "i_newest": 0,
      "i_sgg": 0,
      "h_img": 1025,
      "w_img": 721,
      "date_img_modified": 1645542961387,
      "file_size": "156.24 Kb"
    },
    {
      "id_img": "Original_855619_crop2608_203454380",
      "lik": "UTb0sGqADnbLiHq9qhRMRkSRiLND0Tk7ctN8tpraiicCAs+/FWIpUmueV7n0Nm+cADlsnUiI0QwjY9fZLYU9T5Vy4706IhQgSYlgwrgVRHU=",
      "thub": "UTb0sGqADnbLiHq9qhRMRkSRiLND0Tk7ctN8tpraiicCAs+/FWIpUmueV7n0Nm+calAyG97wRfkJKjYFTXIhU5Vy4706IhQgSYlgwrgVRHU=",
      "albl": [
        "Girls",
        "Original 7"
      ],
      "norl": [
        "Ribbon"
      ],
      "spel": [
        "Girls Hair Black",
        "Girls Sharp Canine Tooth",
        "Girls Student",
        "Girls Bell",
        "Girls Long Hair",
        "Girls Cute Cool",
        "Girls Tie Bows",
        "Girls Eyes Blue"
      ],
      "i_top": 0,
      "i_newest": 0,
      "i_sgg": 0,
      "h_img": 1025,
      "w_img": 721,
      "date_img_modified": 1645542961452,
      "file_size": "145.96 Kb"
    },
    {
      "id_img": "Original_856855_crop2608_2063534207",
      "lik": "UTb0sGqADnbLiHq9qhRMRkSRiLND0Tk7ctN8tpraiidlV8dhr9YpBUWX1z7XXq4WgJpcySFWmOWmskJ99/7IwZVy4706IhQgSYlgwrgVRHU=",
      "thub": "UTb0sGqADnbLiHq9qhRMRkSRiLND0Tk7ctN8tpraiidlV8dhr9YpBUWX1z7XXq4WyKurtUA0rom0HoxGsOhoL5Vy4706IhQgSYlgwrgVRHU=",
      "albl": [
        "Girls",
        "Original 7"
      ],
      "norl": [
        "Ribbon",
        "Aqua Eyes",
        "Heart",
        "Star",
        "Fish",
        "Book"
      ],
      "spel": [
        "Girls Hair Silver",
        "Girls Hair White",
        "Girls Long Hair",
        "Girls Cute Cool",
        "Girls Smile",
        "Girls Tie Bows",
        "Girls Eyes Blue"
      ],
      "i_top": 0,
      "i_newest": 0,
      "i_sgg": 0,
      "h_img": 1353,
      "w_img": 952,
      "date_img_modified": 1645542967518,
      "file_size": "191.29 Kb"
    },
    {
      "id_img": "Original_856855_crop2608_-1797133",
      "lik": "UTb0sGqADnbLiHq9qhRMRkSRiLND0Tk7ctN8tpraiicxoXUwaPk5/sgE3wDfccdwSjzsDdQbmUbpHfe53qZBopVy4706IhQgSYlgwrgVRHU=",
      "thub": "UTb0sGqADnbLiHq9qhRMRkSRiLND0Tk7ctN8tpraiicxoXUwaPk5/sgE3wDfccdwQsNOXAiRZuxx6GmCOZkl2pVy4706IhQgSYlgwrgVRHU=",
      "albl": [
        "Girls",
        "Original 7"
      ],
      "norl": [
        "Ribbon",
        "Aqua Eyes",
        "Heart",
        "Star",
        "Fish",
        "Book"
      ],
      "spel": [
        "Girls Hair Silver",
        "Girls Hair White",
        "Girls Long Hair",
        "Girls Cute Cool",
        "Girls Smile",
        "Girls Tie Bows",
        "Girls Eyes Blue"
      ],
      "i_top": 0,
      "i_newest": 0,
      "i_sgg": 0,
      "h_img": 1353,
      "w_img": 952,
      "date_img_modified": 1645542967598,
      "file_size": "195.84 Kb"
    },
    {
      "id_img": "Original_858535_crop2608_536145871",
      "lik": "UTb0sGqADnbLiHq9qhRMRkSRiLND0Tk7ctN8tpraiieBp4MxARtaJAsPgEVZvqXbe0qcdjKQFvisHJpIfxsll5Vy4706IhQgSYlgwrgVRHU=",
      "thub": "UTb0sGqADnbLiHq9qhRMRkSRiLND0Tk7ctN8tpraiieBp4MxARtaJAsPgEVZvqXb053qelh3atjsmX/IjFyKgJVy4706IhQgSYlgwrgVRHU=",
      "albl": [
        "Scenery Arts",
        "Original 8"
      ],
      "norl": [
        "Ribbon",
        "Flower",
        "Book"
      ],
      "spel": [],
      "i_top": 0,
      "i_newest": 0,
      "i_sgg": 0,
      "h_img": 1157,
      "w_img": 814,
      "date_img_modified": 1645542999905,
      "file_size": "95.88 Kb"
    },
    {
      "id_img": "Original_858535_crop2608_1325496060",
      "lik": "UTb0sGqADnbLiHq9qhRMRkSRiLND0Tk7ctN8tpraiifYYGCH3EYUWCLY6VXKeja/q0NK/b/mDBNr5wct0E47L5Vy4706IhQgSYlgwrgVRHU=",
      "thub": "UTb0sGqADnbLiHq9qhRMRkSRiLND0Tk7ctN8tpraiifYYGCH3EYUWCLY6VXKeja//jqLVZKj17E1nIf8dwBPZZVy4706IhQgSYlgwrgVRHU=",
      "albl": [
        "Scenery Arts",
        "Original 8"
      ],
      "norl": [
        "Ribbon",
        "Flower",
        "Book"
      ],
      "spel": [],
      "i_top": 0,
      "i_newest": 0,
      "i_sgg": 0,
      "h_img": 1157,
      "w_img": 814,
      "date_img_modified": 1645542999971,
      "file_size": "154.92 Kb"
    },
    {
      "id_img": "Original_858535_crop2608_1221321174",
      "lik": "UTb0sGqADnbLiHq9qhRMRkSRiLND0Tk7ctN8tpraiidhDI/NHtfqLSe9GVrGH430ZJ7vYAMcCUV2f5iy/na9F5Vy4706IhQgSYlgwrgVRHU=",
      "thub": "UTb0sGqADnbLiHq9qhRMRkSRiLND0Tk7ctN8tpraiidhDI/NHtfqLSe9GVrGH430WvUqH+zeBN0uvU210pZa2ZVy4706IhQgSYlgwrgVRHU=",
      "albl": [
        "Scenery Arts",
        "Original 8"
      ],
      "norl": [
        "Ribbon",
        "Flower",
        "Book"
      ],
      "spel": [],
      "i_top": 0,
      "i_newest": 0,
      "i_sgg": 0,
      "h_img": 1157,
      "w_img": 814,
      "date_img_modified": 1645543000028,
      "file_size": "175.89 Kb"
    },
    {
      "id_img": "Original_863300_crop2608_1048577342",
      "lik": "UTb0sGqADnbLiHq9qhRMRkSRiLND0Tk7ctN8tpraiidUzb8VGVvbhxm3jz1tkLJ2A6ZiRJXaWQPFTfMdlVRD1pVy4706IhQgSYlgwrgVRHU=",
      "thub": "UTb0sGqADnbLiHq9qhRMRkSRiLND0Tk7ctN8tpraiidUzb8VGVvbhxm3jz1tkLJ2sEHoRy9PspqoQZluzaRYW5Vy4706IhQgSYlgwrgVRHU=",
      "albl": [
        "Girls",
        "Original 8"
      ],
      "norl": [
        "Ribbon",
        "Blonde"
      ],
      "spel": [
        "Girls Student",
        "Girls Hair Yellow",
        "Girls Long Hair",
        "Girls Cute Cool",
        "Girls Tie Bows",
        "Girls Eyes Blue"
      ],
      "i_top": 0,
      "i_newest": 0,
      "i_sgg": 0,
      "h_img": 1030,
      "w_img": 725,
      "date_img_modified": 1645543026123,
      "file_size": "135.94 Kb"
    },
    {
      "id_img": "Original_863300_crop2608_1073840980",
      "lik": "UTb0sGqADnbLiHq9qhRMRkSRiLND0Tk7ctN8tpraiienzO/pjE6dbjqpY2M6qjVvErzwsefmXQjzKKEwZenLLpVy4706IhQgSYlgwrgVRHU=",
      "thub": "UTb0sGqADnbLiHq9qhRMRkSRiLND0Tk7ctN8tpraiienzO/pjE6dbjqpY2M6qjVvHw+x3mrgJWVTPo1B85QNKpVy4706IhQgSYlgwrgVRHU=",
      "albl": [
        "Girls",
        "Original 8"
      ],
      "norl": [
        "Ribbon",
        "Blonde"
      ],
      "spel": [
        "Girls Student",
        "Girls Eyes Yellow",
        "Girls Long Hair",
        "Girls Cute Cool",
        "Girls Smile",
        "Girls Tie Bows",
        "Girls Hair Brow"
      ],
      "i_top": 0,
      "i_newest": 0,
      "i_sgg": 0,
      "h_img": 1030,
      "w_img": 725,
      "date_img_modified": 1645543026184,
      "file_size": "126.54 Kb"
    },
    {
      "id_img": "Original_864244_crop2608_-1644277002",
      "lik": "UTb0sGqADnbLiHq9qhRMRkSRiLND0Tk7ctN8tpraiidnJg/4jBUGZ/QRRkooMX7OI0BBdf/wP/t3soaETc+HgpVy4706IhQgSYlgwrgVRHU=",
      "thub": "UTb0sGqADnbLiHq9qhRMRkSRiLND0Tk7ctN8tpraiidnJg/4jBUGZ/QRRkooMX7OYdZgi8IX851bzM9dFx2CXJVy4706IhQgSYlgwrgVRHU=",
      "albl": [
        "Girls",
        "Original 8"
      ],
      "norl": [
        "Ribbon",
        "Yukata",
        "Lantern",
        "Flower"
      ],
      "spel": [
        "Girls Hair Black",
        "Girls Long Hair",
        "Girls Kimono Yukata Cheongsam",
        "Girls Tie Bows",
        "Girls Eyes Blue"
      ],
      "i_top": 0,
      "i_newest": 0,
      "i_sgg": 0,
      "h_img": 1410,
      "w_img": 992,
      "date_img_modified": 1645543041863,
      "file_size": "243.24 Kb"
    },
    {
      "id_img": "Original_864808_crop2608_500779965",
      "lik": "UTb0sGqADnbLiHq9qhRMRkSRiLND0Tk7ctN8tpraiicGwUPjMqU3m8T7gQKZ1WtvGcgfu19HWYSRHzrv9LzBypVy4706IhQgSYlgwrgVRHU=",
      "thub": "UTb0sGqADnbLiHq9qhRMRkSRiLND0Tk7ctN8tpraiicGwUPjMqU3m8T7gQKZ1Wtvx97HHmE4j/XmdbBp/glJA5Vy4706IhQgSYlgwrgVRHU=",
      "albl": [
        "Girls",
        "Original 8"
      ],
      "norl": [
        "Ribbon",
        "Yukata",
        "Japanese Clothes"
      ],
      "spel": [
        "Girls Short Hair",
        "Girls Hair Blue",
        "Girls Kimono Yukata Cheongsam",
        "Girls Tie Bows",
        "Girls Eyes Blue"
      ],
      "i_top": 0,
      "i_newest": 0,
      "i_sgg": 0,
      "h_img": 1681,
      "w_img": 1183,
      "date_img_modified": 1645543056437,
      "file_size": "300.34 Kb"
    },
    {
      "id_img": "Original_864808_crop2608_1698598762",
      "lik": "UTb0sGqADnbLiHq9qhRMRkSRiLND0Tk7ctN8tpraiiec/Mw33tz3ctr8JQ+4rHQ7N2pJj8jbPk15ZuycE1f5vZVy4706IhQgSYlgwrgVRHU=",
      "thub": "UTb0sGqADnbLiHq9qhRMRkSRiLND0Tk7ctN8tpraiiec/Mw33tz3ctr8JQ+4rHQ7Ocq536Z8Uw0UzDr119xApZVy4706IhQgSYlgwrgVRHU=",
      "albl": [
        "Girls",
        "Original 8"
      ],
      "norl": [
        "Ribbon",
        "Yukata",
        "Japanese Clothes"
      ],
      "spel": [
        "Girls Eyes Pink",
        "Girls Long Hair",
        "Girls Hair Blue",
        "Girls Smile",
        "Girls Kimono Yukata Cheongsam",
        "Girls Tie Bows",
        "Girls Eyes Blue",
        "Girls Hair Brow"
      ],
      "i_top": 0,
      "i_newest": 0,
      "i_sgg": 0,
      "h_img": 1681,
      "w_img": 1183,
      "date_img_modified": 1645543056528,
      "file_size": "336.49 Kb"
    },
    {
      "id_img": "Original_864808_crop2608_124978088",
      "lik": "UTb0sGqADnbLiHq9qhRMRkSRiLND0Tk7ctN8tpraiicwBiIIxTjaJYEGPMAOPcPLsI9s48Yp3UPJdn8d15aeYJVy4706IhQgSYlgwrgVRHU=",
      "thub": "UTb0sGqADnbLiHq9qhRMRkSRiLND0Tk7ctN8tpraiicwBiIIxTjaJYEGPMAOPcPLqOR9a/kkAtZRJ+c6Pu3SiJVy4706IhQgSYlgwrgVRHU=",
      "albl": [
        "Girls",
        "Original 8"
      ],
      "norl": [
        "Ribbon",
        "Yukata",
        "Japanese Clothes"
      ],
      "spel": [
        "Girls Eyes Pink",
        "Girls Long Hair",
        "Girls Cute Cool",
        "Girls Smile",
        "Girls Kimono Yukata Cheongsam",
        "Girls Tie Bows",
        "Girls Hair Brow"
      ],
      "i_top": 0,
      "i_newest": 0,
      "i_sgg": 0,
      "h_img": 1681,
      "w_img": 1183,
      "date_img_modified": 1645543056619,
      "file_size": "288.57 Kb"
    },
    {
      "id_img": "Original_866296_crop2608_1154553847",
      "lik": "UTb0sGqADnbLiHq9qhRMRkSRiLND0Tk7ctN8tpraiicbhzNk576m66quXSt1kKK/xitakfjExghklxtdho08zpVy4706IhQgSYlgwrgVRHU=",
      "thub": "UTb0sGqADnbLiHq9qhRMRkSRiLND0Tk7ctN8tpraiicbhzNk576m66quXSt1kKK/sxTH75JfTRA85gNWmD/svJVy4706IhQgSYlgwrgVRHU=",
      "albl": [
        "Girls",
        "Original 8"
      ],
      "norl": [
        "Ribbon",
        "Aqua Eyes",
        "Yukata",
        "Night",
        "Lantern",
        "Fish",
        "Flower",
        "Festival",
        "Moon"
      ],
      "spel": [
        "Girls Long Hair",
        "Girls Kimono Yukata Cheongsam",
        "Girls Tie Bows",
        "Girls Eyes Blue",
        "Girls Hair Brow"
      ],
      "i_top": 0,
      "i_newest": 0,
      "i_sgg": 0,
      "h_img": 1397,
      "w_img": 983,
      "date_img_modified": 1645543074246,
      "file_size": "288.93 Kb"
    },
    {
      "id_img": "Original_869281_crop2608_-273953488",
      "lik": "UTb0sGqADnbLiHq9qhRMRkSRiLND0Tk7ctN8tpraiifQaHz/fOSRtaQgZhV0fsYcl6+MNP4mLbAr8lGX00uob5Vy4706IhQgSYlgwrgVRHU=",
      "thub": "UTb0sGqADnbLiHq9qhRMRkSRiLND0Tk7ctN8tpraiifQaHz/fOSRtaQgZhV0fsYc9Xjxn9UoMCsbIIm/hhy2h5Vy4706IhQgSYlgwrgVRHU=",
      "albl": [
        "Girls",
        "Original 8"
      ],
      "norl": [
        "Ribbon",
        "Wings",
        "Shoe"
      ],
      "spel": [
        "Girls Hair Silver",
        "Girls Uniform",
        "Girls Short Hair",
        "Girls Eyes Red",
        "Girls Cute Cool",
        "Girls Hair Blue",
        "Girls Smile",
        "Girls Tie Bows"
      ],
      "i_top": 0,
      "i_newest": 0,
      "i_sgg": 0,
      "h_img": 1300,
      "w_img": 915,
      "date_img_modified": 1645543107168,
      "file_size": "100.08 Kb"
    },
    {
      "id_img": "Original_869284_crop2608_-46265357",
      "lik": "UTb0sGqADnbLiHq9qhRMRkSRiLND0Tk7ctN8tpraiidDDH3hY55I+WfLVVl09ZKhGLim6Kv99JLEiSgGyc08ZpVy4706IhQgSYlgwrgVRHU=",
      "thub": "UTb0sGqADnbLiHq9qhRMRkSRiLND0Tk7ctN8tpraiidDDH3hY55I+WfLVVl09ZKhRZdRXDisp/AKYkpxPhDh35Vy4706IhQgSYlgwrgVRHU=",
      "albl": [
        "Girls",
        "Original 8"
      ],
      "norl": [
        "Ribbon",
        "Thigh Highs",
        "Yukata",
        "Bell",
        "Flower"
      ],
      "spel": [
        "Girls Hair Silver",
        "Girls Bell",
        "Sad",
        "Girls Hair Grey",
        "Girls Sad",
        "Girls Long Hair",
        "Girls Cute Cool",
        "Girls Eyes Black",
        "Girls Kimono Yukata Cheongsam",
        "Girls Tie Bows"
      ],
      "i_top": 0,
      "i_newest": 0,
      "i_sgg": 0,
      "h_img": 2535,
      "w_img": 1784,
      "date_img_modified": 1645543108071,
      "file_size": "255.27 Kb"
    },
    {
      "id_img": "Original_870085_crop2608_-1706088228",
      "lik": "UTb0sGqADnbLiHq9qhRMRkSRiLND0Tk7ctN8tpraiicEzj2oS3JTKAZkPnAadwfn8CxBf4Hiejy57VbyjJE8o5Vy4706IhQgSYlgwrgVRHU=",
      "thub": "UTb0sGqADnbLiHq9qhRMRkSRiLND0Tk7ctN8tpraiicEzj2oS3JTKAZkPnAadwfnLPW8Yt6eVo2zDoTKLfuZw5Vy4706IhQgSYlgwrgVRHU=",
      "albl": [
        "Girls",
        "Original 8"
      ],
      "norl": [
        "Ribbon",
        "High Heels",
        "Dagger",
        "Blade",
        "Knife"
      ],
      "spel": [
        "Girls Hair Black",
        "Girls Eyes Brown",
        "Girls Long Hair",
        "Girls Kimono Yukata Cheongsam",
        "Girls Tie Bows"
      ],
      "i_top": 0,
      "i_newest": 0,
      "i_sgg": 0,
      "h_img": 1280,
      "w_img": 901,
      "date_img_modified": 1645543121898,
      "file_size": "94.22 Kb"
    },
    {
      "id_img": "Original_870675_crop2608_-1665630461",
      "lik": "UTb0sGqADnbLiHq9qhRMRkSRiLND0Tk7ctN8tpraiie2asWkzG0dJh1L+m02MAmiJzjhpZv/9RkNEAc7xyL+hZVy4706IhQgSYlgwrgVRHU=",
      "thub": "UTb0sGqADnbLiHq9qhRMRkSRiLND0Tk7ctN8tpraiie2asWkzG0dJh1L+m02MAmiLNY0Kwf86tfqbmq7v1vm+ZVy4706IhQgSYlgwrgVRHU=",
      "albl": [
        "Girls",
        "Original 8"
      ],
      "norl": [
        "Ribbon",
        "Brush",
        "Twintails",
        "Japanese"
      ],
      "spel": [
        "Girls Hair Black",
        "Girls Student",
        "Girls Long Hair",
        "Girls Cute Cool",
        "Girls Tie Bows",
        "Girls Eyes Blue",
        "Girls Hair Brow"
      ],
      "i_top": 0,
      "i_newest": 0,
      "i_sgg": 0,
      "h_img": 1358,
      "w_img": 956,
      "date_img_modified": 1645543129438,
      "file_size": "137.08 Kb"
    },
    {
      "id_img": "Original_871473_crop2608_205508766",
      "lik": "UTb0sGqADnbLiHq9qhRMRkSRiLND0Tk7ctN8tpraiie/rmCB2si9ud52+tz+3XPcpxD1FOhyLL9Nhlwdjd8LLZVy4706IhQgSYlgwrgVRHU=",
      "thub": "UTb0sGqADnbLiHq9qhRMRkSRiLND0Tk7ctN8tpraiie/rmCB2si9ud52+tz+3XPc7cWvdm9cV1O4DKWBcUvj8ZVy4706IhQgSYlgwrgVRHU=",
      "albl": [
        "Girls",
        "Original 8"
      ],
      "norl": [
        "Water",
        "Ribbon",
        "Balloon"
      ],
      "spel": [
        "Girls Hair Black",
        "Sad",
        "Girls Sad",
        "Girls Long Hair",
        "Girls Water Rain",
        "Girls Tie Bows",
        "Girls Eyes Blue"
      ],
      "i_top": 0,
      "i_newest": 0,
      "i_sgg": 0,
      "h_img": 1468,
      "w_img": 1033,
      "date_img_modified": 1645543137555,
      "file_size": "147.60 Kb"
    },
    {
      "id_img": "Original_873398_crop2608_-920222242",
      "lik": "UTb0sGqADnbLiHq9qhRMRkSRiLND0Tk7ctN8tpraiidRyqGvGYqBV9aGUnj3M3cjxiGfMnNJPUiR3GzgFErGHpVy4706IhQgSYlgwrgVRHU=",
      "thub": "UTb0sGqADnbLiHq9qhRMRkSRiLND0Tk7ctN8tpraiidRyqGvGYqBV9aGUnj3M3cjUxjU/4xprb6dLdG/EUrbVJVy4706IhQgSYlgwrgVRHU=",
      "albl": [
        "Girls",
        "Original 9"
      ],
      "norl": [
        "Ribbon",
        "Flower"
      ],
      "spel": [
        "Girls Hair Black",
        "Sad",
        "Girls Eyes Brown",
        "Girls Sad",
        "Girls Long Hair",
        "Girls Maid",
        "Girls Tie Bows"
      ],
      "i_top": 0,
      "i_newest": 0,
      "i_sgg": 0,
      "h_img": 1080,
      "w_img": 760,
      "date_img_modified": 1645543162343,
      "file_size": "125.53 Kb"
    },
    {
      "id_img": "Original_873558_crop2608_-466433436",
      "lik": "UTb0sGqADnbLiHq9qhRMRkSRiLND0Tk7ctN8tpraiieOHKMcDas3tXStwj5R925cLP39SUN32bVskZqB0Fo2l5Vy4706IhQgSYlgwrgVRHU=",
      "thub": "UTb0sGqADnbLiHq9qhRMRkSRiLND0Tk7ctN8tpraiieOHKMcDas3tXStwj5R925c37gQ3pPSSrqYC78+7XQn15Vy4706IhQgSYlgwrgVRHU=",
      "albl": [
        "Girls",
        "Original 9"
      ],
      "norl": [
        "Ribbon",
        "Shirt",
        "Flower"
      ],
      "spel": [
        "Girls Uniform",
        "Girls Long Hair",
        "Girls Hair Blue",
        "Girls Smile",
        "Girls Tie Bows",
        "Girls Eyes Blue"
      ],
      "i_top": 0,
      "i_newest": 0,
      "i_sgg": 0,
      "h_img": 1360,
      "w_img": 957,
      "date_img_modified": 1645543167672,
      "file_size": "195.24 Kb"
    },
    {
      "id_img": "Original_892743_crop2608_-1183943003",
      "lik": "UTb0sGqADnbLiHq9qhRMRkSRiLND0Tk7ctN8tpraiif6Vf2D2cbijBQtSJ9oLOhOY/7BWsuvD14vfwwnbbte/5Vy4706IhQgSYlgwrgVRHU=",
      "thub": "UTb0sGqADnbLiHq9qhRMRkSRiLND0Tk7ctN8tpraiif6Vf2D2cbijBQtSJ9oLOhOYvL+V3ZrjNqFsWoBfXVsNJVy4706IhQgSYlgwrgVRHU=",
      "albl": [
        "Original 10",
        "Girls"
      ],
      "norl": [
        "Ribbon",
        "Statue",
        "Japanese Clothes"
      ],
      "spel": [
        "Girls Hair Black",
        "Girls Long Hair",
        "Girls Eyes Grey",
        "Girls Smile",
        "Girls Eyes Black",
        "Girls Kimono Yukata Cheongsam",
        "Girls Tie Bows"
      ],
      "i_top": 0,
      "i_newest": 0,
      "i_sgg": 0,
      "h_img": 1297,
      "w_img": 913,
      "date_img_modified": 1645543380594,
      "file_size": "167.35 Kb"
    },
    {
      "id_img": "Original_892781_crop2608_2083577650",
      "lik": "UTb0sGqADnbLiHq9qhRMRkSRiLND0Tk7ctN8tpraiifXcHjpqbjr9M75ztARsTZrzZSWWnyZ6aJBFHyHBV7dqpVy4706IhQgSYlgwrgVRHU=",
      "thub": "UTb0sGqADnbLiHq9qhRMRkSRiLND0Tk7ctN8tpraiifXcHjpqbjr9M75ztARsTZraAZgC7SSLLaavEVS9IVTR5Vy4706IhQgSYlgwrgVRHU=",
      "albl": [
        "Original 10",
        "Girls"
      ],
      "norl": [
        "Ribbon",
        "Japanese Clothes"
      ],
      "spel": [
        "Girls Sharp Canine Tooth",
        "Girls Hair Pink",
        "Girls Eyes Brown",
        "Girls Long Hair",
        "Girls Cute Cool",
        "Girls Smile",
        "Girls Kimono Yukata Cheongsam",
        "Girls Tie Bows"
      ],
      "i_top": 0,
      "i_newest": 0,
      "i_sgg": 0,
      "h_img": 1387,
      "w_img": 976,
      "date_img_modified": 1645543382294,
      "file_size": "139.04 Kb"
    },
    {
      "id_img": "Original_892781_crop2608_-1946216033",
      "lik": "UTb0sGqADnbLiHq9qhRMRkSRiLND0Tk7ctN8tpraiicPt0OLlvqfYHqN4Pe+JE6fqOB301PJkcPCcMIYx178k5Vy4706IhQgSYlgwrgVRHU=",
      "thub": "UTb0sGqADnbLiHq9qhRMRkSRiLND0Tk7ctN8tpraiicPt0OLlvqfYHqN4Pe+JE6fFgaFsSB2WjqZzRL5TZbzdJVy4706IhQgSYlgwrgVRHU=",
      "albl": [
        "Original 10",
        "Girls"
      ],
      "norl": [
        "Ribbon",
        "Japanese Clothes"
      ],
      "spel": [
        "Girls Sharp Canine Tooth",
        "Girls Hair Yellow",
        "Girls Hair Pink",
        "Girls Eyes Brown",
        "Girls Long Hair",
        "Girls Cute Cool",
        "Girls Smile",
        "Girls Kimono Yukata Cheongsam",
        "Girls Tie Bows",
        "Girls Eyes Blue"
      ],
      "i_top": 0,
      "i_newest": 0,
      "i_sgg": 0,
      "h_img": 1387,
      "w_img": 976,
      "date_img_modified": 1645543382371,
      "file_size": "184.00 Kb"
    },
    {
      "id_img": "Original_892781_crop2608_1947066067",
      "lik": "UTb0sGqADnbLiHq9qhRMRkSRiLND0Tk7ctN8tpraiicZ5Kk7UJS7TV+X38MkE3408lM821NPHXzIZN6uqaUSvpVy4706IhQgSYlgwrgVRHU=",
      "thub": "UTb0sGqADnbLiHq9qhRMRkSRiLND0Tk7ctN8tpraiicZ5Kk7UJS7TV+X38MkE340jfqcmES0UqRwIDs0UEG5SpVy4706IhQgSYlgwrgVRHU=",
      "albl": [
        "Original 10",
        "Girls"
      ],
      "norl": [
        "Ribbon",
        "Japanese Clothes"
      ],
      "spel": [
        "Girls Hair Yellow",
        "Girls Long Hair",
        "Girls Cute Cool",
        "Girls Smile",
        "Girls Kimono Yukata Cheongsam",
        "Girls Tie Bows",
        "Girls Eyes Blue"
      ],
      "i_top": 0,
      "i_newest": 0,
      "i_sgg": 0,
      "h_img": 1387,
      "w_img": 976,
      "date_img_modified": 1645543382583,
      "file_size": "164.73 Kb"
    },
    {
      "id_img": "Original_893213_crop2608_1173973282",
      "lik": "UTb0sGqADnbLiHq9qhRMRkSRiLND0Tk7ctN8tpraiidikf7gVK1XM2B/nhSNqDFlVPr/NoGejUJ1zAUFuzJcAJVy4706IhQgSYlgwrgVRHU=",
      "thub": "UTb0sGqADnbLiHq9qhRMRkSRiLND0Tk7ctN8tpraiidikf7gVK1XM2B/nhSNqDFlnsClZj4HK9Az5fs0gYYtGZVy4706IhQgSYlgwrgVRHU=",
      "albl": [
        "Original 10",
        "Girls"
      ],
      "norl": [
        "Ribbon",
        "Flower",
        "Japanese Clothes"
      ],
      "spel": [
        "Girls Hair Black",
        "Girls Hair Silver",
        "Girls Hair White",
        "Girls Eyes Red",
        "Girls Long Hair",
        "Girls Eyes Violet",
        "Girls Smile",
        "Girls Kimono Yukata Cheongsam",
        "Girls Tie Bows",
        "Girls Eyes 2 Color"
      ],
      "i_top": 0,
      "i_newest": 0,
      "i_sgg": 0,
      "h_img": 1225,
      "w_img": 862,
      "date_img_modified": 1645543389075,
      "file_size": "210.99 Kb"
    },
    {
      "id_img": "Original_894097_crop2608_-1888309833",
      "lik": "UTb0sGqADnbLiHq9qhRMRkSRiLND0Tk7ctN8tpraiicTkPqt/W8gy+ufomVjJtBOlFIoXnbjTq0UKCFryn/F95Vy4706IhQgSYlgwrgVRHU=",
      "thub": "UTb0sGqADnbLiHq9qhRMRkSRiLND0Tk7ctN8tpraiicTkPqt/W8gy+ufomVjJtBOC8DJzY1DjlvGh3xUVgqt6ZVy4706IhQgSYlgwrgVRHU=",
      "albl": [
        "Original 10",
        "Girls"
      ],
      "norl": [
        "Ribbon",
        "Snow",
        "Winter",
        "Dog",
        "Japanese Clothes"
      ],
      "spel": [
        "Girls Hair Yellow",
        "Girls Short Hair",
        "Girls Cute Cool",
        "Girls Eyes Violet",
        "Girls Kimono Yukata Cheongsam",
        "Girls Tie Bows"
      ],
      "i_top": 0,
      "i_newest": 0,
      "i_sgg": 0,
      "h_img": 1447,
      "w_img": 1018,
      "date_img_modified": 1645543398581,
      "file_size": "205.12 Kb"
    },
    {
      "id_img": "Original_895392_crop2608_-763719656",
      "lik": "UTb0sGqADnbLiHq9qhRMRkSRiLND0Tk7ctN8tpraiiekDpHACB2K8mUo9nMbCJPntggr0MsuCdVcHIWDMD3H05Vy4706IhQgSYlgwrgVRHU=",
      "thub": "UTb0sGqADnbLiHq9qhRMRkSRiLND0Tk7ctN8tpraiiekDpHACB2K8mUo9nMbCJPnySBD4zNQJYoDp37NYgp5bZVy4706IhQgSYlgwrgVRHU=",
      "albl": [
        "Original 10",
        "Girls"
      ],
      "norl": [
        "Ribbon",
        "Thigh Highs",
        "Blonde",
        "Blood",
        "Stuffed Animal",
        "Knife"
      ],
      "spel": [
        "Girls Hair Yellow",
        "Sad",
        "Girls Sad",
        "Girls Long Hair",
        "Girls Eyes Black",
        "Girls Tie Bows"
      ],
      "i_top": 0,
      "i_newest": 0,
      "i_sgg": 0,
      "h_img": 2000,
      "w_img": 1408,
      "date_img_modified": 1645543411257,
      "file_size": "163.60 Kb"
    },
    {
      "id_img": "Original_895407_crop2608_-162745209",
      "lik": "UTb0sGqADnbLiHq9qhRMRkSRiLND0Tk7ctN8tpraiifO9VcOLNIsbhm+EP+UdUGLoef7Q5xfxaxu1b7EZjFwipVy4706IhQgSYlgwrgVRHU=",
      "thub": "UTb0sGqADnbLiHq9qhRMRkSRiLND0Tk7ctN8tpraiifO9VcOLNIsbhm+EP+UdUGL8tOyY3JfqXl9AAh+J99HkpVy4706IhQgSYlgwrgVRHU=",
      "albl": [
        "Original 10",
        "Girls"
      ],
      "norl": [
        "Boots",
        "Sword",
        "Ribbon",
        "Thigh Highs",
        "Blonde"
      ],
      "spel": [
        "Girls Uniform",
        "Girls Hair Yellow",
        "Girls Long Hair",
        "Girls Tie Bows",
        "Girls Eyes Blue"
      ],
      "i_top": 0,
      "i_newest": 0,
      "i_sgg": 0,
      "h_img": 2739,
      "w_img": 1928,
      "date_img_modified": 1645543411979,
      "file_size": "467.91 Kb"
    },
    {
      "id_img": "Original_895653_crop2608_-1744036640",
      "lik": "UTb0sGqADnbLiHq9qhRMRkSRiLND0Tk7ctN8tpraiiceTXOlRUiHOvxlywCK2e0dX0EHcyw/ccmGs45XC9dv25Vy4706IhQgSYlgwrgVRHU=",
      "thub": "UTb0sGqADnbLiHq9qhRMRkSRiLND0Tk7ctN8tpraiiceTXOlRUiHOvxlywCK2e0dSRh8sGnO1h/zOmsvVVMMMpVy4706IhQgSYlgwrgVRHU=",
      "albl": [
        "Original 10",
        "Girls"
      ],
      "norl": [
        "Umbrella",
        "Ribbon",
        "Japanese Clothes"
      ],
      "spel": [
        "Girls Hair Black",
        "Girls Long Hair",
        "Girls Smile",
        "Girls Eyes Black",
        "Girls Kimono Yukata Cheongsam",
        "Girls Tie Bows"
      ],
      "i_top": 0,
      "i_newest": 0,
      "i_sgg": 0,
      "h_img": 1200,
      "w_img": 844,
      "date_img_modified": 1645543417399,
      "file_size": "121.57 Kb"
    },
    {
      "id_img": "Original_905795_crop2608_-816272011",
      "lik": "UTb0sGqADnbLiHq9qhRMRkSRiLND0Tk7ctN8tpraiicxSwwEOCflBdAMkk4QFw20LmqTyBgfNnAnf53NdGrcaZVy4706IhQgSYlgwrgVRHU=",
      "thub": "UTb0sGqADnbLiHq9qhRMRkSRiLND0Tk7ctN8tpraiicxSwwEOCflBdAMkk4QFw20Pu1+oPGsCDtVd98zk5SAR5Vy4706IhQgSYlgwrgVRHU=",
      "albl": [
        "Original 10",
        "Girls"
      ],
      "norl": [
        "Ribbon",
        "Flower",
        "Skirt",
        "Japanese Clothes"
      ],
      "spel": [
        "Girls Short Hair",
        "Girls Hair Pink",
        "Girls Eyes Red",
        "Girls Cute Cool",
        "Girls Smile",
        "Girls Kimono Yukata Cheongsam",
        "Girls Tie Bows"
      ],
      "i_top": 0,
      "i_newest": 0,
      "i_sgg": 0,
      "h_img": 2500,
      "w_img": 1760,
      "date_img_modified": 1645543588263,
      "file_size": "467.75 Kb"
    },
    {
      "id_img": "PixivFantasia_697638_crop2608_-630501759",
      "lik": "UTb0sGqADnbLiHq9qhRMRkSRiLND0Tk7ctN8tpraiic7Pgtmv+0yPevws0grYzK58x3TXNAkcOnqD2VaanuoU5Vy4706IhQgSYlgwrgVRHU=",
      "thub": "UTb0sGqADnbLiHq9qhRMRkSRiLND0Tk7ctN8tpraiic7Pgtmv+0yPevws0grYzK5yKTQMJHlJKB14EMAwqh6zZVy4706IhQgSYlgwrgVRHU=",
      "albl": [
        "Girls",
        "Pixiv Fantasia"
      ],
      "norl": [
        "Ribbon",
        "Pantyhose"
      ],
      "spel": [
        "Girls Hair Silver",
        "Girls Hair White",
        "Girls Uniform",
        "Girls Horns",
        "Sad",
        "Girls Eyes Red",
        "Girls Sad",
        "Girls Long Hair",
        "Girls Cute Cool",
        "Girls Tie Bows"
      ],
      "i_top": 0,
      "i_newest": 0,
      "i_sgg": 0,
      "h_img": 2829,
      "w_img": 1991,
      "date_img_modified": 1645544690261,
      "file_size": "360.18 Kb"
    },
    {
      "id_img": "PixivFantasia_697638_crop2608_-88701519",
      "lik": "UTb0sGqADnbLiHq9qhRMRkSRiLND0Tk7ctN8tpraiifrCsndN7rou25BsAuD0LiSIjNL3Y+Iv2vlG/r41wYbVpVy4706IhQgSYlgwrgVRHU=",
      "thub": "UTb0sGqADnbLiHq9qhRMRkSRiLND0Tk7ctN8tpraiifrCsndN7rou25BsAuD0LiS8+pykvYeu97pIrhbzfAY4JVy4706IhQgSYlgwrgVRHU=",
      "albl": [
        "Girls",
        "Pixiv Fantasia"
      ],
      "norl": [
        "Ribbon",
        "Pantyhose"
      ],
      "spel": [
        "Girls Hair Silver",
        "Girls Hair White",
        "Girls Horns",
        "Sad",
        "Girls Eyes Red",
        "Girls Sad",
        "Girls Long Hair",
        "Girls Cute Cool",
        "Girls Tie Bows"
      ],
      "i_top": 0,
      "i_newest": 0,
      "i_sgg": 0,
      "h_img": 2829,
      "w_img": 1991,
      "date_img_modified": 1645544690440,
      "file_size": "345.71 Kb"
    },
    {
      "id_img": "PuellaMagiMadokaMagica_677466_crop2608_1416194223",
      "lik": "UTb0sGqADnbLiHq9qhRMRkSRiLND0Tk7ctN8tpraiif+Ekhbo7+IfD9zic0LOCkp67NuCUVhpcRS1VFuKwNjfZVy4706IhQgSYlgwrgVRHU=",
      "thub": "UTb0sGqADnbLiHq9qhRMRkSRiLND0Tk7ctN8tpraiif+Ekhbo7+IfD9zic0LOCkpIFufrWG6lddTDAToEdWJUJVy4706IhQgSYlgwrgVRHU=",
      "albl": [
        "Girls",
        "Puella Magi Madoka Magica"
      ],
      "norl": [
        "Madoka Kaname",
        "Ultimate Madoka",
        "Ribbon",
        "Twintails",
        "Wings",
        "Petal",
        "Homura Akemi",
        "Glove",
        "Feather",
        "Sitting",
        "Pantyhose",
        "Headband"
      ],
      "spel": [
        "Girls Hair Black",
        "Girls Hair Orange",
        "Girls Eyes Yellow",
        "Girls Eyes Brown",
        "Girls Long Hair",
        "Girls Tie Bows"
      ],
      "i_top": 0,
      "i_newest": 0,
      "i_sgg": 0,
      "h_img": 1234,
      "w_img": 868,
      "date_img_modified": 1645544747596,
      "file_size": "184.80 Kb"
    },
    {
      "id_img": "SoranoMukoudeSakimasuyouni_792663_crop2608_-1615276646",
      "lik": "UTb0sGqADnbLiHq9qhRMRkSRiLND0Tk7ctN8tpraiifps1XAQTsnGxFqwbZFBSIE2jwSBMrcBMPM43uiOUZ8CZVy4706IhQgSYlgwrgVRHU=",
      "thub": "UTb0sGqADnbLiHq9qhRMRkSRiLND0Tk7ctN8tpraiifps1XAQTsnGxFqwbZFBSIE4SZu9gXVfhq3/awc4Cmv/pVy4706IhQgSYlgwrgVRHU=",
      "albl": [
        "Girls",
        "Sora no Mukou de Sakimasu you ni"
      ],
      "norl": [
        "Ribbon",
        "Wink",
        "Urara Haruki",
        "Blush"
      ],
      "spel": [
        "Girls Hair Orange",
        "Girls Sharp Canine Tooth",
        "Girls Eyes Yellow",
        "Girls Long Hair",
        "Girls Hair Blue",
        "Girls Smile",
        "Girls Tie Bows",
        "Girls Eyes Blue"
      ],
      "i_top": 0,
      "i_newest": 0,
      "i_sgg": 0,
      "h_img": 1080,
      "w_img": 760,
      "date_img_modified": 1645545410718,
      "file_size": "121.88 Kb"
    },
    {
      "id_img": "SoranoMukoudeSakimasuyouni_792672_crop2608_661604664",
      "lik": "UTb0sGqADnbLiHq9qhRMRkSRiLND0Tk7ctN8tpraiifzytpBSPQIxcsQrAzu+gkUZdsOC2AupD2W+QkbdUTCbJVy4706IhQgSYlgwrgVRHU=",
      "thub": "UTb0sGqADnbLiHq9qhRMRkSRiLND0Tk7ctN8tpraiifzytpBSPQIxcsQrAzu+gkUXVQcAoIn6B7F7Bln2Y5pH5Vy4706IhQgSYlgwrgVRHU=",
      "albl": [
        "Girls",
        "Sora no Mukou de Sakimasu you ni"
      ],
      "norl": [
        "Ribbon",
        "Blonde",
        "Headband",
        "Hairpin",
        "Urara Haruki"
      ],
      "spel": [
        "Girls Hair Yellow",
        "Girls Long Hair",
        "Girls Smile",
        "Girls Tie Bows",
        "Girls Eyes Blue"
      ],
      "i_top": 0,
      "i_newest": 0,
      "i_sgg": 0,
      "h_img": 1080,
      "w_img": 760,
      "date_img_modified": 1645545411288,
      "file_size": "96.42 Kb"
    },
    {
      "id_img": "TheiDOLMSTER_875654_crop2608_1184469809",
      "lik": "UTb0sGqADnbLiHq9qhRMRkSRiLND0Tk7ctN8tpraiidfDbzDUC9z4DMRisyBOG8HAb1LP9tepEPKCg1S5LdZvJVy4706IhQgSYlgwrgVRHU=",
      "thub": "UTb0sGqADnbLiHq9qhRMRkSRiLND0Tk7ctN8tpraiidfDbzDUC9z4DMRisyBOG8H4bLAhMUO8msG0orjfy+ZcZVy4706IhQgSYlgwrgVRHU=",
      "albl": [
        "Girls",
        "The iDOLMSTER"
      ],
      "norl": [
        "Ribbon",
        "Wink",
        "Blonde",
        "Twintails",
        "iDOLMSTER Cinderella Girls",
        "Asuka Ninomiya",
        "Flower",
        "Ranko Kanzaki"
      ],
      "spel": [
        "Girls Hair Orange",
        "Girls Hair Yellow",
        "Girls Eyes Brown",
        "Girls Long Hair",
        "Girls Cute Cool",
        "Girls Tie Bows"
      ],
      "i_top": 0,
      "i_newest": 0,
      "i_sgg": 0,
      "h_img": 3082,
      "w_img": 2169,
      "date_img_modified": 1645545985027,
      "file_size": "575.33 Kb"
    },
    {
      "id_img": "TheiDOLMSTER_875654_crop2608_1594542558",
      "lik": "UTb0sGqADnbLiHq9qhRMRkSRiLND0Tk7ctN8tpraiifsIAYnvVcclvswVXHSXjJq99JeVODkz4S7Ry8mLg/2X5Vy4706IhQgSYlgwrgVRHU=",
      "thub": "UTb0sGqADnbLiHq9qhRMRkSRiLND0Tk7ctN8tpraiifsIAYnvVcclvswVXHSXjJqqc8Wc14ukCo9QOKEebcVoJVy4706IhQgSYlgwrgVRHU=",
      "albl": [
        "Girls",
        "The iDOLMSTER"
      ],
      "norl": [
        "Ribbon",
        "Wink",
        "Blonde",
        "Twintails",
        "iDOLMSTER Cinderella Girls",
        "Asuka Ninomiya",
        "Flower",
        "Ranko Kanzaki"
      ],
      "spel": [
        "Girls Hair Silver",
        "Girls Hair Orange",
        "Girls Hair Yellow",
        "Girls Eyes Brown",
        "Girls Long Hair",
        "Girls Cute Cool",
        "Girls Tie Bows"
      ],
      "i_top": 0,
      "i_newest": 0,
      "i_sgg": 0,
      "h_img": 3082,
      "w_img": 2169,
      "date_img_modified": 1645545985273,
      "file_size": "689.53 Kb"
    },
    {
      "id_img": "TheiDOLMSTER_875654_crop2608_-155473228",
      "lik": "UTb0sGqADnbLiHq9qhRMRkSRiLND0Tk7ctN8tpraiic0PAh7BUzG/xtpUi/fKFBRRzLtEv0Cjd00FU4D2LK8jJVy4706IhQgSYlgwrgVRHU=",
      "thub": "UTb0sGqADnbLiHq9qhRMRkSRiLND0Tk7ctN8tpraiic0PAh7BUzG/xtpUi/fKFBRrgSutvpclnqUspcJT4ZwEpVy4706IhQgSYlgwrgVRHU=",
      "albl": [
        "Girls",
        "The iDOLMSTER"
      ],
      "norl": [
        "Ribbon",
        "Wink",
        "Blonde",
        "Twintails",
        "iDOLMSTER Cinderella Girls",
        "Asuka Ninomiya",
        "Flower",
        "Ranko Kanzaki"
      ],
      "spel": [
        "Girls Hair Silver",
        "Girls Hair Grey",
        "Girls Long Hair",
        "Girls Cute Cool",
        "Girls Tie Bows"
      ],
      "i_top": 0,
      "i_newest": 0,
      "i_sgg": 0,
      "h_img": 3082,
      "w_img": 2169,
      "date_img_modified": 1645545985484,
      "file_size": "631.39 Kb"
    },
    {
      "id_img": "Touhou_215602_crop2608_1833232895",
      "lik": "UTb0sGqADnbLiHq9qhRMRkSRiLND0Tk7ctN8tpraiiffcyLqOSMKEJOEidU7nl+RSTzjxFMMLhCZlwGLbb7w/JVy4706IhQgSYlgwrgVRHU=",
      "thub": "UTb0sGqADnbLiHq9qhRMRkSRiLND0Tk7ctN8tpraiiffcyLqOSMKEJOEidU7nl+RDpyIY1JKEeejxw6N85Tt1JVy4706IhQgSYlgwrgVRHU=",
      "albl": [
        "Girls",
        "Touhou"
      ],
      "norl": [
        "Sword",
        "Ribbon",
        "Butterfly",
        "Yuyuko Saigyouji",
        "Youmu Konpaku",
        "Petal",
        "Tree",
        "Flower"
      ],
      "spel": [
        "Girls Short Hair",
        "Girls Hair Pink",
        "Girls Hats",
        "Girls Eyes Violet",
        "Girls Smile",
        "Girls Kimono Yukata Cheongsam",
        "Girls Tie Bows",
        "Girls Witch"
      ],
      "i_top": 0,
      "i_newest": 0,
      "i_sgg": 0,
      "h_img": 1157,
      "w_img": 814,
      "date_img_modified": 1645546557464,
      "file_size": "121.79 Kb"
    },
    {
      "id_img": "Touhou_672934_crop2608_355341081",
      "lik": "UTb0sGqADnbLiHq9qhRMRkSRiLND0Tk7ctN8tpraiic1p2VtkW3UWt1Ygtff2Mb/9eQCop3qKZwuTUyBQB70HpVy4706IhQgSYlgwrgVRHU=",
      "thub": "UTb0sGqADnbLiHq9qhRMRkSRiLND0Tk7ctN8tpraiic1p2VtkW3UWt1Ygtff2Mb/n6MBrszLWxpflxSXjeNWgpVy4706IhQgSYlgwrgVRHU=",
      "albl": [
        "Unrefined",
        "Touhou"
      ],
      "norl": [
        "Reimu Hakurei",
        "Ribbon",
        "Sakuya Izayoi",
        "Marisa Kirisame",
        "Blonde",
        "Koakuma Touhou",
        "Alice Margatroid",
        "Video Game",
        "Book"
      ],
      "spel": [],
      "i_top": 0,
      "i_newest": 0,
      "i_sgg": 0,
      "h_img": 1200,
      "w_img": 844,
      "date_img_modified": 1645546661322,
      "file_size": "78.00 Kb"
    },
    {
      "id_img": "Touhou_672934_crop2608_-629215290",
      "lik": "UTb0sGqADnbLiHq9qhRMRkSRiLND0Tk7ctN8tpraiifp3ZskkeV3WT+E2nYaxAlZm87w3pshYewZZRoXaviWXZVy4706IhQgSYlgwrgVRHU=",
      "thub": "UTb0sGqADnbLiHq9qhRMRkSRiLND0Tk7ctN8tpraiifp3ZskkeV3WT+E2nYaxAlZgegA1gqyrGK4H4bZEMUr9pVy4706IhQgSYlgwrgVRHU=",
      "albl": [
        "Unrefined",
        "Touhou"
      ],
      "norl": [
        "Reimu Hakurei",
        "Ribbon",
        "Sakuya Izayoi",
        "Marisa Kirisame",
        "Blonde",
        "Koakuma Touhou",
        "Alice Margatroid",
        "Video Game",
        "Book"
      ],
      "spel": [],
      "i_top": 0,
      "i_newest": 0,
      "i_sgg": 0,
      "h_img": 1200,
      "w_img": 844,
      "date_img_modified": 1645546661374,
      "file_size": "90.11 Kb"
    },
    {
      "id_img": "Touhou_672934_crop2608_-88660020",
      "lik": "UTb0sGqADnbLiHq9qhRMRkSRiLND0Tk7ctN8tpraiie+SbzMqErPMBqyU4V/OGnnrbNfxEnDEq1dZvplf1lJT5Vy4706IhQgSYlgwrgVRHU=",
      "thub": "UTb0sGqADnbLiHq9qhRMRkSRiLND0Tk7ctN8tpraiie+SbzMqErPMBqyU4V/OGnnYdabwo/JuzcGwBF+1GngopVy4706IhQgSYlgwrgVRHU=",
      "albl": [
        "Unrefined",
        "Touhou"
      ],
      "norl": [
        "Reimu Hakurei",
        "Ribbon",
        "Sakuya Izayoi",
        "Marisa Kirisame",
        "Blonde",
        "Koakuma Touhou",
        "Alice Margatroid",
        "Video Game",
        "Book"
      ],
      "spel": [],
      "i_top": 0,
      "i_newest": 0,
      "i_sgg": 0,
      "h_img": 1200,
      "w_img": 844,
      "date_img_modified": 1645546661455,
      "file_size": "80.39 Kb"
    },
    {
      "id_img": "Touhou_793207_crop2608_1446969061",
      "lik": "UTb0sGqADnbLiHq9qhRMRkSRiLND0Tk7ctN8tpraiidpm3Ie4VPxD/eBVc+B3ewU8Pc4H0ss8iCbc/s+yCTkfJVy4706IhQgSYlgwrgVRHU=",
      "thub": "UTb0sGqADnbLiHq9qhRMRkSRiLND0Tk7ctN8tpraiidpm3Ie4VPxD/eBVc+B3ewUcnMxCNvimM9WW+Tk0x+Pl5Vy4706IhQgSYlgwrgVRHU=",
      "albl": [
        "Girls",
        "Touhou"
      ],
      "norl": [
        "Reimu Hakurei",
        "Ribbon",
        "Sunbeam",
        "bow Clothing",
        "Blush"
      ],
      "spel": [
        "Girls Short Hair",
        "Sad",
        "Girls Sad",
        "Girls Kimono Yukata Cheongsam",
        "Girls Tie Bows",
        "Girls Witch",
        "Girls Hair Brow"
      ],
      "i_top": 0,
      "i_newest": 0,
      "i_sgg": 0,
      "h_img": 1200,
      "w_img": 844,
      "date_img_modified": 1645547171471,
      "file_size": "131.40 Kb"
    },
    {
      "id_img": "Touhou_874884_crop2608_1242945564",
      "lik": "UTb0sGqADnbLiHq9qhRMRkSRiLND0Tk7ctN8tpraiierAFnFpahLIA6TU+Ys3EFGp8pKBP/EVJPyQDg80ShdiJVy4706IhQgSYlgwrgVRHU=",
      "thub": "UTb0sGqADnbLiHq9qhRMRkSRiLND0Tk7ctN8tpraiierAFnFpahLIA6TU+Ys3EFGbNCL+aOQLJH4ejfqz/y8jJVy4706IhQgSYlgwrgVRHU=",
      "albl": [
        "Girls",
        "Touhou"
      ],
      "norl": [
        "Ribbon",
        "Momiji Inubashiri",
        "Blush"
      ],
      "spel": [
        "Girls Hair Silver",
        "Girls Hair White",
        "Girls Short Hair",
        "Girls Eyes Red",
        "Girls Hats",
        "Girls Ears Neko",
        "Girls Tie Bows",
        "Girls Witch"
      ],
      "i_top": 0,
      "i_newest": 0,
      "i_sgg": 0,
      "h_img": 2576,
      "w_img": 1813,
      "date_img_modified": 1645547259401,
      "file_size": "476.58 Kb"
    },
    {
      "id_img": "VampireKnight_723045_crop2608_782578863",
      "lik": "UTb0sGqADnbLiHq9qhRMRkSRiLND0Tk7ctN8tpraiidahePBE2vXWr8eEJo6fzmBpxuUfZuGI9Gc64O8ZXM7HJVy4706IhQgSYlgwrgVRHU=",
      "thub": "UTb0sGqADnbLiHq9qhRMRkSRiLND0Tk7ctN8tpraiidahePBE2vXWr8eEJo6fzmBTRuffw+YjSL7VhyA2FfKTJVy4706IhQgSYlgwrgVRHU=",
      "albl": [
        "Vampire Knight"
      ],
      "norl": [
        "Ribbon",
        "Butterfly",
        "Yuki Cross",
        "Yuki Kuran",
        "Petal"
      ],
      "spel": [],
      "i_top": 0,
      "i_newest": 0,
      "i_sgg": 0,
      "h_img": 1200,
      "w_img": 844,
      "date_img_modified": 1645547708602,
      "file_size": "102.30 Kb"
    },
    {
      "id_img": "Vocaloid_691973_crop2608_-44991869",
      "lik": "UTb0sGqADnbLiHq9qhRMRkSRiLND0Tk7ctN8tpraiieUrb7d1SH3XvANAmDOumILeYxeFuJMa83C2lDNK6wBXZVy4706IhQgSYlgwrgVRHU=",
      "thub": "UTb0sGqADnbLiHq9qhRMRkSRiLND0Tk7ctN8tpraiieUrb7d1SH3XvANAmDOumILC5AuOTAllbTj1im9I96YwJVy4706IhQgSYlgwrgVRHU=",
      "albl": [
        "Vocaloid",
        "Girls"
      ],
      "norl": [
        "Water",
        "Ribbon",
        "Headdress",
        "Twintails",
        "Hatsune Miku",
        "bow Clothing",
        "Blush"
      ],
      "spel": [
        "Girls Student",
        "Girls Long Hair",
        "Girls Music",
        "Girls Hair Blue",
        "Girls Tie Bows",
        "Girls Eyes Blue"
      ],
      "i_top": 0,
      "i_newest": 0,
      "i_sgg": 0,
      "h_img": 1366,
      "w_img": 961,
      "date_img_modified": 1645547998848,
      "file_size": "221.30 Kb"
    },
    {
      "id_img": "Vocaloid_696828_crop2608_-588200697",
      "lik": "UTb0sGqADnbLiHq9qhRMRkSRiLND0Tk7ctN8tpraiiebdpM7xZB8nbLVfvGF80z6/qb84xg7ElJpehffzF5b9pVy4706IhQgSYlgwrgVRHU=",
      "thub": "UTb0sGqADnbLiHq9qhRMRkSRiLND0Tk7ctN8tpraiiebdpM7xZB8nbLVfvGF80z6OyQo6c2GhVUNSHuV+PhMepVy4706IhQgSYlgwrgVRHU=",
      "albl": [
        "Vocaloid",
        "Girls"
      ],
      "norl": [
        "Ribbon",
        "Twintails",
        "Hatsune Miku",
        "Fish",
        "Digital Art"
      ],
      "spel": [
        "Girls Hair Silver",
        "Girls Eyes Silver",
        "Girls Student",
        "Girls Hair White",
        "Girls Eyes White",
        "Sad",
        "Girls Sad",
        "Girls Long Hair",
        "Girls Water Rain",
        "Girls Tie Bows"
      ],
      "i_top": 0,
      "i_newest": 0,
      "i_sgg": 0,
      "h_img": 923,
      "w_img": 649,
      "date_img_modified": 1645548005098,
      "file_size": "84.66 Kb"
    },
    {
      "id_img": "Vocaloid_793205_crop2608_-1037318526",
      "lik": "UTb0sGqADnbLiHq9qhRMRkSRiLND0Tk7ctN8tpraiidbuO4qtolrd8x1XGsHW+n/t9bctmkf0y+QWlL/ZXwEHpVy4706IhQgSYlgwrgVRHU=",
      "thub": "UTb0sGqADnbLiHq9qhRMRkSRiLND0Tk7ctN8tpraiidbuO4qtolrd8x1XGsHW+n/Fb0xBAN17eVIClI/54u1XZVy4706IhQgSYlgwrgVRHU=",
      "albl": [
        "Vocaloid",
        "Girls"
      ],
      "norl": [
        "Water",
        "Ribbon",
        "Twintails",
        "Hatsune Miku",
        "Bubble",
        "bow Clothing",
        "Fish",
        "School Uniform",
        "Skirt"
      ],
      "spel": [
        "Girls Hair Silver",
        "Girls Student",
        "Girls Hair White",
        "Girls Long Hair",
        "Girls Water Rain",
        "Girls Tie Bows",
        "Girls Eyes Blue"
      ],
      "i_top": 0,
      "i_newest": 0,
      "i_sgg": 0,
      "h_img": 1037,
      "w_img": 730,
      "date_img_modified": 1645548265584,
      "file_size": "102.36 Kb"
    },
    {
      "id_img": "Original_830915_crop2608_1239313782",
      "lik": "UTb0sGqADnbLiHq9qhRMRkSRiLND0Tk7ctN8tpraiiffkrA4zI+bHXN5kNs48oednKhNQLAt+A+JHvQyRig4W5Vy4706IhQgSYlgwrgVRHU=",
      "thub": "UTb0sGqADnbLiHq9qhRMRkSRiLND0Tk7ctN8tpraiiffkrA4zI+bHXN5kNs48oedgu2T7HthiVcvFnSPHUHcw5Vy4706IhQgSYlgwrgVRHU=",
      "albl": [
        "Girls",
        "Original 5"
      ],
      "norl": [
        "Ribbon",
        "Cat",
        "Braid"
      ],
      "spel": [
        "Girls Hair Black",
        "Girls Eyes Pink",
        "Girls Long Hair",
        "Girls Cute Cool",
        "Girls Hats",
        "Girls Eyes Violet",
        "Girls Hair Blue",
        "Girls Tie Bows"
      ],
      "i_top": 0,
      "i_newest": 0,
      "i_sgg": 0,
      "h_img": 1200,
      "w_img": 844,
      "date_img_modified": 1661398494470,
      "file_size": "225.72 Kb"
    },
    {
      "id_img": "Touhou_841005_crop2608_-1427552469",
      "lik": "UTb0sGqADnbLiHq9qhRMRkSRiLND0Tk7ctN8tpraiic4BF5QqkIaP5BQIYG+pCQBTnUf4+iI11O5ubMAKFQALJVy4706IhQgSYlgwrgVRHU=",
      "thub": "UTb0sGqADnbLiHq9qhRMRkSRiLND0Tk7ctN8tpraiic4BF5QqkIaP5BQIYG+pCQBi6nzFO91Kx/9EKFNQ4j3AZVy4706IhQgSYlgwrgVRHU=",
      "albl": [
        "Girls",
        "Touhou"
      ],
      "norl": [
        "Ribbon",
        "Cat",
        "Rumia Touhou"
      ],
      "spel": [
        "Girls Student",
        "Girls Hair Yellow",
        "Girls Short Hair",
        "Girls Eyes Red",
        "Girls Cute Cool",
        "Girls Tie Bows"
      ],
      "i_top": 0,
      "i_newest": 0,
      "i_sgg": 0,
      "h_img": 1200,
      "w_img": 844,
      "date_img_modified": 1661402787346,
      "file_size": "105.24 Kb"
    }
  ]
}